izi18n/__init__.py
izi18n/core.py
izi18n/i18n.py
izi18n/utils.py
izi18n/__pycache__/__init__.cpython-37.pyc
izi18n/__pycache__/core.cpython-37.pyc
izi18n/__pycache__/i18n.cpython-37.pyc
izi18n/__pycache__/utils.cpython-37.pyc
izi18n-1.0.2.dist-info/LICENSE
izi18n-1.0.2.dist-info/METADATA
izi18n-1.0.2.dist-info/WHEEL
izi18n-1.0.2.dist-info/top_level.txt
izi18n-1.0.2.dist-info/RECORD
