Metadata-Version: 2.1
Name: izi18n
Version: 1.0.2
Summary: Simple python library for language Internationalisation
Home-page: https://github.com/cnfilms/izi18n
Author: Joel ONIPOH
Author-email: technique@cinego.net
Project-URL: Bug Tracker, https://github.com/cnfilms/izi18n/issues
Project-URL: Changelog, https://github.com/cnfilms/izi18n/releases
Keywords: python,i18n,Internationalisation,Internationalization,language,po,read .po file,json,translate pattern,interpolate translation
Classifier: Programming Language :: Python :: 3
Classifier: License :: OSI Approved :: MIT License
Classifier: Operating System :: OS Independent
Requires-Python: >=3.3
License-File: LICENSE
